{
  "383": {
    "type": "table",
    "polist": {
      "1097-006": {
        "ovf": {
          "d234o": [
            "50*2"
          ],
          "d233o": [
            "50*2"
          ],
          "d252o": [
            "50*4",
            "16",
            "18",
            "34",
            "42",
            "49",
            "64",
            "36"
          ],
          "d363o": [
            "50*3"
          ]
        }
      },
      "1098-006": {
        "ovf": {
          "d234o": [
            "50*2"
          ],
          "d233o": [
            "50*4"
          ],
          "d251o": [
            "50*2",
            "14",
            "34",
            "33*2"
          ],
          "d363o": [
            "50*3"
          ]
        }
      },
      "1099-005": {
        "ovf": {
          "d252o": [
            "50"
          ],
          "d315o": [
            "50*19",
            "32"
          ],
          "d345o": [
            "50*2"
          ],
          "d363o": [
            "50*12"
          ]
        }
      },
      "1101-005": {
        "ovf": {
          "d252o": [
            "50",
            "57"
          ],
          "d254o": [
            "44"
          ],
          "d315o": [
            "50*5"
          ]
        }
      },
      "1102-005": {
        "ovf": {
          "d314o": [
            "50*4"
          ],
          "d243o": [
            "50"
          ],
          "d251o": [
            "50*6",
            "11"
          ],
          "d345o": [
            "50*4"
          ]
        }
      },
      "1113-006": {
        "ovf": {
          "d241o": [
            "20*4",
            "14",
            "18",
            "40",
            "24",
            "31",
            "39"
          ]
        }
      },
      "1114-006": {
        "ovf": {
          "d241o": [
            "20",
            "23",
            "24"
          ]
        }
      },
      "1115-006": {
        "ovf": {
          "d243o": [
            "20"
          ]
        }
      },
      "1116-006": {
        "ovf": {
          "d241o": [
            "20*2",
            "14",
            "18",
            "40",
            "24",
            "31",
            "39"
          ]
        }
      },
      "1117-006": {
        "ovf": {
          "d232o": [
            "40*3",
            "18"
          ],
          "d244o": [
            "40*4",
            "21"
          ]
        }
      },
      "1118-006": {
        "ovf": {
          "d231o": [
            "20",
            "19",
            "40*4",
            "24"
          ]
        }
      },
      "1121-001": {
        "ovf": {
          "d132o": [
            "20*8",
            "12",
            "10",
            "24"
          ],
          "d231o": [
            "20"
          ]
        }
      },
      "1122-001": {
        "ovf": {
          "d231o": [
            "20*4",
            "3",
            "11",
            "15",
            "40*5"
          ]
        }
      },
      "1125-003": {
        "ovf": {
          "d222o": [
            "40*3",
            "46"
          ]
        }
      },
      "1126-003": {
        "ovf": {
          "d221o": [
            "20",
            "2",
            "15",
            "11",
            "40",
            "48"
          ]
        }
      },
      "1129-005": {
        "ovf": {
          "d231o": [
            "6"
          ],
          "d232o": [
            "20*5",
            "7",
            "40*3",
            "39",
            "31"
          ],
          "d352o": [
            "20*2"
          ]
        }
      },
      "1130-005": {
        "ovf": {
          "d231o": [
            "20*8",
            "4",
            "5",
            "17",
            "19",
            "40*2",
            "36"
          ],
          "d325o": [
            "20*8"
          ],
          "d352o": [
            "20",
            "40*5"
          ]
        }
      },
      "1131-005": {
        "ovf": {
          "d222o": [
            "20",
            "25"
          ]
        }
      },
      "1132-005": {
        "ovf": {
          "d231o": [
            "2"
          ]
        }
      },
      "1133-005": {
        "ovf": {
          "d232o": [
            "40*3",
            "8",
            "7"
          ]
        }
      },
      "1134-005": {
        "ovf": {
          "d231o": [
            "20*6",
            "7",
            "13",
            "18",
            "40*3",
            "31"
          ]
        }
      },
      "1135-005": {
        "ovf": {
          "d222o": [
            "20*8",
            "17"
          ],
          "d325o": [
            "20*10"
          ],
          "d352o": [
            "20*5"
          ]
        }
      },
      "1136-005": {
        "ovf": {
          "d221o": [
            "20",
            "40*3",
            "21"
          ]
        }
      },
      "1137-005": {
        "ovf": {
          "d212o": [
            "20*5",
            "23",
            "18",
            "11",
            "9",
            "17"
          ],
          "d222o": [
            "38",
            "4"
          ],
          "d244o": [
            "40*2"
          ]
        }
      },
      "1138-005": {
        "ovf": {
          "d211o": [
            "20*3",
            "8",
            "14",
            "15",
            "24",
            "17",
            "27",
            "40",
            "39"
          ],
          "d244o": [
            "20"
          ]
        }
      },
      "1139-005": {
        "ovf": {
          "d213o": [
            "20",
            "21"
          ],
          "d211o": [
            "6"
          ],
          "d212o": [
            "20*3",
            "7",
            "17",
            "40*3",
            "22",
            "35",
            "39"
          ]
        }
      },
      "1140-005": {
        "ovf": {
          "d211o": [
            "20*7",
            "23",
            "19",
            "18",
            "40*3"
          ]
        }
      },
      "1141-005": {
        "ovf": {
          "d212o": [
            "20*2",
            "14",
            "13",
            "19",
            "16",
            "40*3",
            "39"
          ]
        }
      },
      "1142-005": {
        "ovf": {
          "d211o": [
            "20",
            "14"
          ],
          "d244o": [
            "40*3"
          ]
        }
      },
      "1143-005": {
        "ovf": {
          "d211o": [
            "20",
            "9"
          ]
        }
      },
      "1144-005": {
        "ovf": {
          "d211o": [
            "20",
            "9",
            "19"
          ]
        }
      },
      "1263-006": {
        "ovf": {
          "d244o": [
            "40"
          ]
        }
      },
      "1264-006": {
        "ovf": {
          "d244o": [
            "40"
          ]
        }
      },
      "1285-005": {
        "ovf": {
          "d211o": [
            "40"
          ],
          "d234o": [
            "40*5"
          ],
          "d244o": [
            "40*2"
          ]
        }
      },
      "1286-005": {
        "ovf": {
          "d234o": [
            "20",
            "19",
            "40*2"
          ],
          "d254o": [
            "20"
          ],
          "d244o": [
            "20*4",
            "39"
          ]
        }
      },
      "1287-005": {
        "ovf": {
          "d212o": [
            "20*3",
            "2",
            "16",
            "39"
          ],
          "d234o": [
            "20*2"
          ],
          "d244o": [
            "20"
          ],
          "d213o": [
            "40"
          ]
        }
      },
      "1288-005": {
        "ovf": {
          "d211o": [
            "20",
            "19"
          ],
          "d234o": [
            "20*2"
          ],
          "d244o": [
            "20*2"
          ],
          "d212o": [
            "3",
            "4",
            "18",
            "14",
            "20",
            "39"
          ],
          "d213o": [
            "40",
            "33"
          ]
        }
      },
      "1289-005": {
        "ovf": {
          "d214o": [
            "50*12"
          ],
          "d234o": [
            "50*12"
          ],
          "d252o": [
            "50*5"
          ],
          "d253o": [
            "50*3"
          ]
        }
      },
      "1290-005": {
        "ovf": {
          "d214o": [
            "50*12"
          ],
          "d224o": [
            "50*12"
          ],
          "d243o": [
            "50*2"
          ],
          "d251o": [
            "50*6"
          ],
          "d213o": [
            "14"
          ]
        }
      },
      "1291-005": {
        "ovf": {
          "d252o": [
            "50*2",
            "47",
            "31*2"
          ]
        }
      },
      "1292-005": {
        "ovf": {
          "d224o": [
            "50"
          ],
          "d251o": [
            "50*9",
            "29"
          ]
        }
      },
      "1293-005": {
        "ovf": {
          "d234o": [
            "50*8"
          ],
          "d242o": [
            "50",
            "11",
            "15",
            "33",
            "41"
          ],
          "d254o": [
            "50*17"
          ],
          "d253o": [
            "50*4"
          ]
        }
      },
      "1294-005": {
        "ovf": {
          "d224o": [
            "50*7"
          ],
          "d243o": [
            "50*4"
          ],
          "d241o": [
            "50*2",
            "28",
            "21",
            "29",
            "30"
          ],
          "d253o": [
            "50*3"
          ]
        }
      },
      "1295-005": {
        "ovf": {
          "d244o": [
            "50*3"
          ],
          "d254o": [
            "50*9"
          ],
          "d242o": [
            "20"
          ]
        }
      },
      "1296-005": {
        "ovf": {
          "d214o": [
            "50*2"
          ],
          "d244o": [
            "50*9"
          ],
          "d254o": [
            "50*3"
          ],
          "d253o": [
            "50*2"
          ],
          "d241o": [
            "10"
          ]
        }
      },
      "1297-005": {
        "ovf": {
          "d242o": [
            "50*2"
          ]
        }
      },
      "1298-005": {
        "ovf": {
          "d241o": [
            "50*4",
            "13"
          ]
        }
      },
      "1342-003": {
        "ovf": {
          "d353o": [
            "50*6"
          ]
        }
      },
      "1343-003": {
        "ovf": {
          "d223o": [
            "50*2"
          ]
        }
      },
      "1345-003": {
        "ovf": {
          "d213o": [
            "50"
          ]
        }
      },
      "1346-003": {
        "ovf": {
          "d231o": [
            "50*2"
          ]
        }
      },
      "1347-003": {
        "ovf": {
          "d213o": [
            "50*3"
          ],
          "d243o": [
            "50"
          ],
          "d253o": [
            "24"
          ]
        }
      },
      "1348-003": {
        "ovf": {
          "d223o": [
            "50"
          ],
          "d253o": [
            "19"
          ]
        }
      },
      "1349-003": {
        "ovf": {
          "d224o": [
            "50*2"
          ]
        }
      },
      "1350-003": {
        "ovf": {
          "d224o": [
            "50*10"
          ],
          "d223o": [
            "50*3"
          ]
        }
      },
      "2816-006": {
        "ovf": {
          "d234o": [
            "60*4",
            "40"
          ]
        }
      },
      "2817-006": {
        "ovf": {
          "d211o": [
            "60"
          ],
          "d234o": [
            "60*4"
          ]
        }
      },
      "2827-006": {
        "ovf": {
          "d234o": [
            "60"
          ]
        }
      },
      "2822-???": {
        "ovf": {
          "d211o": [
            "30"
          ],
          "d244o": [
            "60*5"
          ]
        }
      },
      "2823-???": {
        "ovf": {
          "d244o": [
            "60*5"
          ]
        }
      },
      "1227-008": {
        "counts": [],
        "ovf": {
          "d362o": [
            "20"
          ],
          "d361o": [
            "20"
          ],
          "d353o": [
            "20"
          ],
          "d351o": [
            "20"
          ],
          "d314o": [
            "20*2"
          ],
          "d3121": [
            "20*2"
          ]
        }
      },
      "1228-008": {
        "counts": [],
        "ovf": {
          "d361o": [
            "20*2"
          ],
          "d353o": [
            "20*6"
          ],
          "d314o": [
            "20*3"
          ],
          "d3122": [
            "20"
          ],
          "d214o": [
            "17",
            "18"
          ]
        }
      },
      "1229-009": {
        "counts": [],
        "ovf": {}
      },
      "1229-010": {
        "counts": [],
        "ovf": {
          "d361o": [
            "20"
          ],
          "d351o": [
            "20"
          ],
          "d3123": [
            "20*3"
          ]
        }
      },
      "1230-010": {
        "counts": [],
        "ovf": {
          "d351o": [
            "20"
          ],
          "d3143": [
            "20"
          ]
        }
      },
      "1245-008": {
        "counts": [],
        "ovf": {
          "d3131": [
            "20*12"
          ],
          "d3125": [
            "20"
          ]
        }
      },
      "1246-007": {
        "counts": [],
        "ovf": {
          "d345o": [
            "20"
          ]
        }
      },
      "1246-008": {
        "counts": [],
        "ovf": {
          "d362o": [
            "20*7"
          ],
          "d361o": [
            "20*2"
          ],
          "d345o": [
            "20*6"
          ],
          "d3135": [
            "20*7"
          ],
          "d3126": [
            "20"
          ]
        }
      },
      "1247-008": {
        "counts": [],
        "ovf": {
          "d344o": [
            "20"
          ],
          "d334o": [
            "20*3"
          ],
          "d3221": [
            "20*3"
          ],
          "d361o": [
            "20"
          ]
        }
      },
      "1248-008": {
        "counts": [],
        "ovf": {
          "d3223": [
            "20*6"
          ],
          "d335o": [
            "20*6"
          ],
          "d361o": [
            "10"
          ]
        }
      },
      "1250-010": {
        "counts": [],
        "ovf": {
          "d353o": [
            "20"
          ],
          "d352o": [
            "20*2"
          ],
          "d3226": [
            "20*2"
          ]
        }
      },
      "1251-009": {
        "counts": [],
        "ovf": {
          "d351o": [
            "20*2"
          ]
        }
      },
      "1251-010": {
        "counts": [],
        "ovf": {
          "d3111": [
            "20*3"
          ]
        }
      },
      "1252-009": {
        "counts": [],
        "ovf": {
          "d351o": [
            "20"
          ],
          "d3112": [
            "20*3"
          ],
          "d345o": [
            "19"
          ]
        }
      },
      "1100-005": {
        "counts": [],
        "ovf": {
          "d314o": [
            "50*6"
          ],
          "d345o": [
            "50*7"
          ]
        }
      },
      "1147-007": {
        "counts": [],
        "ovf": {
          "d363o": [
            "20*4"
          ],
          "d352o": [
            "20*2"
          ]
        }
      },
      "1148-007": {
        "counts": [],
        "ovf": {
          "d363o": [
            "20*5"
          ],
          "d315o": [
            "20*2"
          ],
          "d361o": [
            "14"
          ]
        }
      },
      "1149-007": {
        "counts": [],
        "ovf": {
          "d363o": [
            "20*2"
          ],
          "d344o": [
            "20*5"
          ],
          "d325o": [
            "20*6"
          ],
          "d3423": [
            "20*3"
          ],
          "d352o": [
            "10"
          ]
        }
      },
      "1150-007": {
        "counts": [],
        "ovf": {
          "d361o": [
            "20*2"
          ],
          "d334o": [
            "20*8"
          ],
          "d315o": [
            "20*3"
          ],
          "d3424": [
            "20*3"
          ]
        }
      },
      "1153-007": {
        "counts": [],
        "ovf": {
          "d361o": [
            "20"
          ],
          "d3431": [
            "20*3",
            "19"
          ],
          "d325o": [
            "20",
            "10"
          ]
        }
      },
      "1157-007": {
        "counts": [],
        "ovf": {
          "d361o": [
            "20",
            "12"
          ],
          "d3435": [
            "14",
            "20*5"
          ],
          "d324o": [
            "20"
          ]
        }
      },
      "1158-007": {
        "counts": [],
        "ovf": {
          "d361o": [
            "20"
          ],
          "d3436": [
            "20*6"
          ],
          "d345o": [
            "20"
          ]
        }
      },
      "1161-007": {
        "counts": [],
        "ovf": {}
      },
      "1162-007": {
        "counts": [],
        "ovf": {
          "d345o": [
            "20"
          ],
          "d314o": [
            "20"
          ]
        }
      },
      "1165-007": {
        "counts": [],
        "ovf": {
          "d361o": [
            "20"
          ],
          "d344o": [
            "20"
          ],
          "d334o": [
            "20*4"
          ],
          "d324o": [
            "20*2"
          ],
          "d314o": [
            "20*3"
          ],
          "d3312": [
            "20",
            "10"
          ],
          "d3411": [
            "20*2",
            "18"
          ]
        }
      },
      "1166-007": {
        "counts": [],
        "ovf": {
          "d345o": [
            "20*2"
          ],
          "d344o": [
            "20*3"
          ],
          "d314o": [
            "20"
          ],
          "d3412": [
            "20*3"
          ]
        }
      },
      "1167-007": {
        "counts": [],
        "ovf": {
          "d3413": [
            "20*2",
            "19"
          ]
        }
      },
      "1168-007": {
        "counts": [],
        "ovf": {
          "d334o": [
            "20"
          ],
          "d3414": [
            "20"
          ]
        }
      },
      "1171-007": {
        "counts": [],
        "ovf": {
          "d3415": [
            "20",
            "12"
          ]
        }
      },
      "1172-007": {
        "counts": [],
        "ovf": {
          "d351o": [
            "20"
          ],
          "d3416": [
            "20*3"
          ]
        }
      },
      "1221-007": {
        "counts": [],
        "ovf": {
          "d353o": [
            "20*3"
          ]
        }
      },
      "1221-009": {
        "counts": [],
        "ovf": {
          "d352o": [
            "20*10"
          ],
          "d351o": [
            "20*7"
          ],
          "d345o": [
            "20*4"
          ],
          "d335o": [
            "20*6",
            "18",
            "11"
          ],
          "d325o": [
            "20*7"
          ],
          "d315o": [
            "20*5"
          ],
          "d3231": [
            "20*3"
          ]
        }
      },
      "1222-007": {
        "counts": [],
        "ovf": {
          "d353o": [
            "20*5"
          ],
          "d3232": [
            "20*2"
          ]
        }
      },
      "1222-009": {
        "counts": [],
        "ovf": {
          "d362o": [
            "20*3"
          ],
          "d361o": [
            "20*2",
            "10"
          ],
          "d314o": [
            "20*4",
            "18*2",
            "19",
            "17"
          ]
        }
      },
      "1223-008": {
        "counts": [],
        "ovf": {
          "d361o": [
            "20"
          ],
          "d325o": [
            "20"
          ],
          "d3233": [
            "20*3"
          ],
          "d351o": [
            "8"
          ]
        }
      },
      "1224-007": {
        "counts": [],
        "ovf": {
          "d351o": [
            "20",
            "24"
          ],
          "d3234": [
            "19"
          ]
        }
      },
      "1224-008": {
        "counts": [],
        "ovf": {
          "d361o": [
            "20"
          ],
          "d351o": [
            "20*5"
          ],
          "d325o": [
            "20"
          ],
          "d3234": [
            "20*3"
          ],
          "d335o": [
            "15"
          ]
        }
      },
      "1225-008": {
        "counts": [],
        "ovf": {
          "d363o": [
            "20*12"
          ],
          "d351o": [
            "20*3"
          ],
          "d344o": [
            "20*4"
          ],
          "d335o": [
            "20*4",
            "16",
            "19",
            "18*2",
            "15"
          ],
          "d334o": [
            "20*3"
          ],
          "d324o": [
            "20*2"
          ],
          "d315o": [
            "20*8",
            "18*2"
          ],
          "d3235": [
            "20*4"
          ]
        }
      },
      "1226-008": {
        "counts": [],
        "ovf": {
          "d345o": [
            "20"
          ],
          "d325o": [
            "20"
          ],
          "d3236": [
            "20*4"
          ],
          "d335o": [
            "20*6"
          ],
          "d361o": [
            "8"
          ]
        }
      },
      "1227-007": {
        "counts": [],
        "ovf": {
          "d353o": [
            "20*2"
          ],
          "d3121": [
            "20"
          ]
        }
      }
    }
  }
}